<?xml version="1.0" encoding="UTF-8"?>
<!DOCTYPE mapper PUBLIC "-//mybatis.org//DTD Mapper 3.0//EN" "http://mybatis.org/dtd/mybatis-3-mapper.dtd">
<mapper namespace="com.zym.Design1.dao.GoodsTradeMapper">
  <resultMap id="BaseResultMap" type="com.zym.Design1.entity.GoodsTrade">
    <!--
      WARNING - @mbg.generated
      This element is automatically generated by MyBatis Generator, do not modify.
      This element was generated on Wed May 16 16:55:04 CST 2018.
    -->
    <id column="id" jdbcType="BIGINT" property="id" />
    <result column="date" jdbcType="TIMESTAMP" property="date" />
    <result column="goods_id" jdbcType="INTEGER" property="goodsId" />
    <result column="goods_name" jdbcType="VARCHAR" property="goodsName" />
    <result column="goods_price" jdbcType="DECIMAL" property="goodsPrice" />
    <result column="num" jdbcType="INTEGER" property="num" />
    <result column="buyer_id" jdbcType="INTEGER" property="buyerId" />
    <result column="buyer_uid" jdbcType="VARCHAR" property="buyerUid" />
    <result column="state" jdbcType="CHAR" property="state" />
    <result column="name" jdbcType="VARCHAR" property="name" />
    <result column="phone" jdbcType="VARCHAR" property="phone" />
    <result column="address" jdbcType="VARCHAR" property="address" />
    <result column="remark" jdbcType="VARCHAR" property="remark" />
    <result column="cart" jdbcType="VARCHAR" property="cart" />
  </resultMap>
  <sql id="Example_Where_Clause">
    <!--
      WARNING - @mbg.generated
      This element is automatically generated by MyBatis Generator, do not modify.
      This element was generated on Wed May 16 16:55:04 CST 2018.
    -->
    <where>
      <foreach collection="oredCriteria" item="criteria" separator="or">
        <if test="criteria.valid">
          <trim prefix="(" prefixOverrides="and" suffix=")">
            <foreach collection="criteria.criteria" item="criterion">
              <choose>
                <when test="criterion.noValue">
                  and ${criterion.condition}
                </when>
                <when test="criterion.singleValue">
                  and ${criterion.condition} #{criterion.value}
                </when>
                <when test="criterion.betweenValue">
                  and ${criterion.condition} #{criterion.value} and #{criterion.secondValue}
                </when>
                <when test="criterion.listValue">
                  and ${criterion.condition}
                  <foreach close=")" collection="criterion.value" item="listItem" open="(" separator=",">
                    #{listItem}
                  </foreach>
                </when>
              </choose>
            </foreach>
          </trim>
        </if>
      </foreach>
    </where>
  </sql>
  <sql id="Update_By_Example_Where_Clause">
    <!--
      WARNING - @mbg.generated
      This element is automatically generated by MyBatis Generator, do not modify.
      This element was generated on Wed May 16 16:55:04 CST 2018.
    -->
    <where>
      <foreach collection="example.oredCriteria" item="criteria" separator="or">
        <if test="criteria.valid">
          <trim prefix="(" prefixOverrides="and" suffix=")">
            <foreach collection="criteria.criteria" item="criterion">
              <choose>
                <when test="criterion.noValue">
                  and ${criterion.condition}
                </when>
                <when test="criterion.singleValue">
                  and ${criterion.condition} #{criterion.value}
                </when>
                <when test="criterion.betweenValue">
                  and ${criterion.condition} #{criterion.value} and #{criterion.secondValue}
                </when>
                <when test="criterion.listValue">
                  and ${criterion.condition}
                  <foreach close=")" collection="criterion.value" item="listItem" open="(" separator=",">
                    #{listItem}
                  </foreach>
                </when>
              </choose>
            </foreach>
          </trim>
        </if>
      </foreach>
    </where>
  </sql>
  <sql id="Base_Column_List">
    <!--
      WARNING - @mbg.generated
      This element is automatically generated by MyBatis Generator, do not modify.
      This element was generated on Wed May 16 16:55:04 CST 2018.
    -->
    id, date, goods_id, goods_name, goods_price, num, buyer_id, buyer_uid, state, name, 
    phone, address, remark, cart
  </sql>
  <select id="selectByExample" parameterType="com.zym.Design1.entity.GoodsTradeExample" resultMap="BaseResultMap">
    <!--
      WARNING - @mbg.generated
      This element is automatically generated by MyBatis Generator, do not modify.
      This element was generated on Wed May 16 16:55:04 CST 2018.
    -->
    select
    <if test="distinct">
      distinct
    </if>
    <include refid="Base_Column_List" />
    from goods_trade
    <if test="_parameter != null">
      <include refid="Example_Where_Clause" />
    </if>
    <if test="orderByClause != null">
      order by ${orderByClause}
    </if>
  </select>
  <select id="selectByPrimaryKey" parameterType="java.lang.Long" resultMap="BaseResultMap">
    <!--
      WARNING - @mbg.generated
      This element is automatically generated by MyBatis Generator, do not modify.
      This element was generated on Wed May 16 16:55:04 CST 2018.
    -->
    select 
    <include refid="Base_Column_List" />
    from goods_trade
    where id = #{id,jdbcType=BIGINT}
  </select>
  <delete id="deleteByPrimaryKey" parameterType="java.lang.Long">
    <!--
      WARNING - @mbg.generated
      This element is automatically generated by MyBatis Generator, do not modify.
      This element was generated on Wed May 16 16:55:04 CST 2018.
    -->
    delete from goods_trade
    where id = #{id,jdbcType=BIGINT}
  </delete>
  <delete id="deleteByExample" parameterType="com.zym.Design1.entity.GoodsTradeExample">
    <!--
      WARNING - @mbg.generated
      This element is automatically generated by MyBatis Generator, do not modify.
      This element was generated on Wed May 16 16:55:04 CST 2018.
    -->
    delete from goods_trade
    <if test="_parameter != null">
      <include refid="Example_Where_Clause" />
    </if>
  </delete>
  <insert id="insert" keyColumn="id" keyProperty="id" parameterType="com.zym.Design1.entity.GoodsTrade" useGeneratedKeys="true">
    <!--
      WARNING - @mbg.generated
      This element is automatically generated by MyBatis Generator, do not modify.
      This element was generated on Wed May 16 16:55:04 CST 2018.
    -->
    insert into goods_trade (date, goods_id, goods_name, 
      goods_price, num, buyer_id, 
      buyer_uid, state, name, 
      phone, address, remark, 
      cart)
    values (#{date,jdbcType=TIMESTAMP}, #{goodsId,jdbcType=INTEGER}, #{goodsName,jdbcType=VARCHAR}, 
      #{goodsPrice,jdbcType=DECIMAL}, #{num,jdbcType=INTEGER}, #{buyerId,jdbcType=INTEGER}, 
      #{buyerUid,jdbcType=VARCHAR}, #{state,jdbcType=CHAR}, #{name,jdbcType=VARCHAR}, 
      #{phone,jdbcType=VARCHAR}, #{address,jdbcType=VARCHAR}, #{remark,jdbcType=VARCHAR}, 
      #{cart,jdbcType=VARCHAR})
  </insert>
  <insert id="insertSelective" keyColumn="id" keyProperty="id" parameterType="com.zym.Design1.entity.GoodsTrade" useGeneratedKeys="true">
    <!--
      WARNING - @mbg.generated
      This element is automatically generated by MyBatis Generator, do not modify.
      This element was generated on Wed May 16 16:55:04 CST 2018.
    -->
    insert into goods_trade
    <trim prefix="(" suffix=")" suffixOverrides=",">
      <if test="date != null">
        date,
      </if>
      <if test="goodsId != null">
        goods_id,
      </if>
      <if test="goodsName != null">
        goods_name,
      </if>
      <if test="goodsPrice != null">
        goods_price,
      </if>
      <if test="num != null">
        num,
      </if>
      <if test="buyerId != null">
        buyer_id,
      </if>
      <if test="buyerUid != null">
        buyer_uid,
      </if>
      <if test="state != null">
        state,
      </if>
      <if test="name != null">
        name,
      </if>
      <if test="phone != null">
        phone,
      </if>
      <if test="address != null">
        address,
      </if>
      <if test="remark != null">
        remark,
      </if>
      <if test="cart != null">
        cart,
      </if>
    </trim>
    <trim prefix="values (" suffix=")" suffixOverrides=",">
      <if test="date != null">
        #{date,jdbcType=TIMESTAMP},
      </if>
      <if test="goodsId != null">
        #{goodsId,jdbcType=INTEGER},
      </if>
      <if test="goodsName != null">
        #{goodsName,jdbcType=VARCHAR},
      </if>
      <if test="goodsPrice != null">
        #{goodsPrice,jdbcType=DECIMAL},
      </if>
      <if test="num != null">
        #{num,jdbcType=INTEGER},
      </if>
      <if test="buyerId != null">
        #{buyerId,jdbcType=INTEGER},
      </if>
      <if test="buyerUid != null">
        #{buyerUid,jdbcType=VARCHAR},
      </if>
      <if test="state != null">
        #{state,jdbcType=CHAR},
      </if>
      <if test="name != null">
        #{name,jdbcType=VARCHAR},
      </if>
      <if test="phone != null">
        #{phone,jdbcType=VARCHAR},
      </if>
      <if test="address != null">
        #{address,jdbcType=VARCHAR},
      </if>
      <if test="remark != null">
        #{remark,jdbcType=VARCHAR},
      </if>
      <if test="cart != null">
        #{cart,jdbcType=VARCHAR},
      </if>
    </trim>
  </insert>
  <select id="countByExample" parameterType="com.zym.Design1.entity.GoodsTradeExample" resultType="java.lang.Long">
    <!--
      WARNING - @mbg.generated
      This element is automatically generated by MyBatis Generator, do not modify.
      This element was generated on Wed May 16 16:55:04 CST 2018.
    -->
    select count(*) from goods_trade
    <if test="_parameter != null">
      <include refid="Example_Where_Clause" />
    </if>
  </select>
  <update id="updateByExampleSelective" parameterType="map">
    <!--
      WARNING - @mbg.generated
      This element is automatically generated by MyBatis Generator, do not modify.
      This element was generated on Wed May 16 16:55:04 CST 2018.
    -->
    update goods_trade
    <set>
      <if test="record.id != null">
        id = #{record.id,jdbcType=BIGINT},
      </if>
      <if test="record.date != null">
        date = #{record.date,jdbcType=TIMESTAMP},
      </if>
      <if test="record.goodsId != null">
        goods_id = #{record.goodsId,jdbcType=INTEGER},
      </if>
      <if test="record.goodsName != null">
        goods_name = #{record.goodsName,jdbcType=VARCHAR},
      </if>
      <if test="record.goodsPrice != null">
        goods_price = #{record.goodsPrice,jdbcType=DECIMAL},
      </if>
      <if test="record.num != null">
        num = #{record.num,jdbcType=INTEGER},
      </if>
      <if test="record.buyerId != null">
        buyer_id = #{record.buyerId,jdbcType=INTEGER},
      </if>
      <if test="record.buyerUid != null">
        buyer_uid = #{record.buyerUid,jdbcType=VARCHAR},
      </if>
      <if test="record.state != null">
        state = #{record.state,jdbcType=CHAR},
      </if>
      <if test="record.name != null">
        name = #{record.name,jdbcType=VARCHAR},
      </if>
      <if test="record.phone != null">
        phone = #{record.phone,jdbcType=VARCHAR},
      </if>
      <if test="record.address != null">
        address = #{record.address,jdbcType=VARCHAR},
      </if>
      <if test="record.remark != null">
        remark = #{record.remark,jdbcType=VARCHAR},
      </if>
      <if test="record.cart != null">
        cart = #{record.cart,jdbcType=VARCHAR},
      </if>
    </set>
    <if test="_parameter != null">
      <include refid="Update_By_Example_Where_Clause" />
    </if>
  </update>
  <update id="updateByExample" parameterType="map">
    <!--
      WARNING - @mbg.generated
      This element is automatically generated by MyBatis Generator, do not modify.
      This element was generated on Wed May 16 16:55:04 CST 2018.
    -->
    update goods_trade
    set id = #{record.id,jdbcType=BIGINT},
      date = #{record.date,jdbcType=TIMESTAMP},
      goods_id = #{record.goodsId,jdbcType=INTEGER},
      goods_name = #{record.goodsName,jdbcType=VARCHAR},
      goods_price = #{record.goodsPrice,jdbcType=DECIMAL},
      num = #{record.num,jdbcType=INTEGER},
      buyer_id = #{record.buyerId,jdbcType=INTEGER},
      buyer_uid = #{record.buyerUid,jdbcType=VARCHAR},
      state = #{record.state,jdbcType=CHAR},
      name = #{record.name,jdbcType=VARCHAR},
      phone = #{record.phone,jdbcType=VARCHAR},
      address = #{record.address,jdbcType=VARCHAR},
      remark = #{record.remark,jdbcType=VARCHAR},
      cart = #{record.cart,jdbcType=VARCHAR}
    <if test="_parameter != null">
      <include refid="Update_By_Example_Where_Clause" />
    </if>
  </update>
  <update id="updateByPrimaryKeySelective" parameterType="com.zym.Design1.entity.GoodsTrade">
    <!--
      WARNING - @mbg.generated
      This element is automatically generated by MyBatis Generator, do not modify.
      This element was generated on Wed May 16 16:55:04 CST 2018.
    -->
    update goods_trade
    <set>
      <if test="date != null">
        date = #{date,jdbcType=TIMESTAMP},
      </if>
      <if test="goodsId != null">
        goods_id = #{goodsId,jdbcType=INTEGER},
      </if>
      <if test="goodsName != null">
        goods_name = #{goodsName,jdbcType=VARCHAR},
      </if>
      <if test="goodsPrice != null">
        goods_price = #{goodsPrice,jdbcType=DECIMAL},
      </if>
      <if test="num != null">
        num = #{num,jdbcType=INTEGER},
      </if>
      <if test="buyerId != null">
        buyer_id = #{buyerId,jdbcType=INTEGER},
      </if>
      <if test="buyerUid != null">
        buyer_uid = #{buyerUid,jdbcType=VARCHAR},
      </if>
      <if test="state != null">
        state = #{state,jdbcType=CHAR},
      </if>
      <if test="name != null">
        name = #{name,jdbcType=VARCHAR},
      </if>
      <if test="phone != null">
        phone = #{phone,jdbcType=VARCHAR},
      </if>
      <if test="address != null">
        address = #{address,jdbcType=VARCHAR},
      </if>
      <if test="remark != null">
        remark = #{remark,jdbcType=VARCHAR},
      </if>
      <if test="cart != null">
        cart = #{cart,jdbcType=VARCHAR},
      </if>
    </set>
    where id = #{id,jdbcType=BIGINT}
  </update>
  <update id="updateByPrimaryKey" parameterType="com.zym.Design1.entity.GoodsTrade">
    <!--
      WARNING - @mbg.generated
      This element is automatically generated by MyBatis Generator, do not modify.
      This element was generated on Wed May 16 16:55:04 CST 2018.
    -->
    update goods_trade
    set date = #{date,jdbcType=TIMESTAMP},
      goods_id = #{goodsId,jdbcType=INTEGER},
      goods_name = #{goodsName,jdbcType=VARCHAR},
      goods_price = #{goodsPrice,jdbcType=DECIMAL},
      num = #{num,jdbcType=INTEGER},
      buyer_id = #{buyerId,jdbcType=INTEGER},
      buyer_uid = #{buyerUid,jdbcType=VARCHAR},
      state = #{state,jdbcType=CHAR},
      name = #{name,jdbcType=VARCHAR},
      phone = #{phone,jdbcType=VARCHAR},
      address = #{address,jdbcType=VARCHAR},
      remark = #{remark,jdbcType=VARCHAR},
      cart = #{cart,jdbcType=VARCHAR}
    where id = #{id,jdbcType=BIGINT}
  </update>
</mapper>